{
  "products": [
    {
      "name": "Classic Handmade Bag",
      "description": "Premium hand-stitched leather bag — roomy, durable, and stylish for everyday use.",
      "price": 79.99,
      "featured": true,
      "image": "https://res.cloudinary.com/dejeaec3b/image/upload/v1757706524/mohair-products/rt2cjr7yhlyxfrf1st3i.jpg",
      "color": "red",
      "colorHex": "#fa0000",
      "category": "Bags",
      "rating": 4,
      "reviewCount": 128,
      "oldPrice": "99.99",
      "id": "gen_1923016067"
    },
    {
      "name": "Elegant Wool Hat",
      "description": "Slim-fit wool hat with a modern cut — lightweight and warm.",
      "price": 200,
      "featured": true,
      "image": "https://res.cloudinary.com/dejeaec3b/image/upload/v1757706604/mohair-products/bujehunkr6pthiciuvef.jpg",
      "color": "Brown",
      "colorHex": "#d78c09",
      "category": "Hats",
      "rating": 4,
      "reviewCount": 136,
      "oldPrice": "159.99",
      "id": "gen_173623544"
    },
    {
      "name": "Handcrafted Leather Shoes",
      "description": "Comfort-first leather shoes with handcrafted finishing and cushioned insole.",
      "price": 129.99,
      "featured": true,
      "image": "https://res.cloudinary.com/dejeaec3b/image/upload/v1757763678/mohair-products/yettpzrnzsxc8pdcddk2.jpg",
      "color": "Brown",
      "colorHex": "#db8814",
      "category": "Footwear",
      "rating": 4,
      "reviewCount": 123,
      "oldPrice": "159.99",
      "id": "gen_1229552406"
    }
  ],
  "lastUpdated": "2025-09-23T12:25:35.719Z"
}